xain_proto/__init__.py
xain_proto/fl/__init__.py
xain_proto/fl/coordinator_pb2.py
xain_proto/fl/coordinator_pb2_grpc.py
xain_proto/np/__init__.py
xain_proto/np/ndarray_pb2.py
xain_proto/np/ndarray_pb2_grpc.py
xain_proto/np/utils.py
xain_proto-0.6.0.dist-info/METADATA
xain_proto-0.6.0.dist-info/WHEEL
xain_proto-0.6.0.dist-info/top_level.txt
xain_proto-0.6.0.dist-info/RECORD
