Metadata-Version: 2.1
Name: xain-proto
Version: 0.6.0
Summary: XAIN Protocol Buffers
Home-page: https://github.com/xainag/xain-proto
Author: ['XAIN AG']
Author-email: services@xain.io
License: Apache License Version 2.0
Platform: UNKNOWN
Classifier: Development Status :: 3 - Alpha
Classifier: Intended Audience :: Developers
Classifier: Intended Audience :: Information Technology
Classifier: Intended Audience :: Science/Research
Classifier: Topic :: Scientific/Engineering
Classifier: Topic :: Software Development
Classifier: Topic :: Software Development :: Libraries
Classifier: Topic :: Software Development :: Libraries :: Application Frameworks
Classifier: Topic :: Software Development :: Libraries :: Python Modules
Classifier: License :: OSI Approved :: Apache Software License
Classifier: Programming Language :: Python :: 3 :: Only
Classifier: Programming Language :: Python :: 3.6
Classifier: Programming Language :: Python :: 3.7
Classifier: Programming Language :: Python :: 3.8
Classifier: Operating System :: MacOS :: MacOS X
Classifier: Operating System :: POSIX :: Linux
Requires-Python: >=3.6
Requires-Dist: numpy (~=1.15)
Requires-Dist: protobuf (~=3.9)
Provides-Extra: dev
Requires-Dist: twine (==2.0.0) ; extra == 'dev'
Requires-Dist: wheel (==0.33.6) ; extra == 'dev'
Requires-Dist: isort (==4.3.21) ; extra == 'dev'
Requires-Dist: pytest (==5.3.2) ; extra == 'dev'
Provides-Extra: test
Requires-Dist: pytest (==5.3.2) ; extra == 'test'
